pypreproc/__int__.py
pypreproc/cluster.py
pypreproc/convert.py
pypreproc/correct.py
pypreproc/create.py
pypreproc/customer.py
pypreproc/helper.py
pypreproc-0.182.dist-info/LICENSE.txt
pypreproc-0.182.dist-info/METADATA
pypreproc-0.182.dist-info/WHEEL
pypreproc-0.182.dist-info/top_level.txt
pypreproc-0.182.dist-info/RECORD
