Metadata-Version: 2.1
Name: pypreproc
Version: 0.182
Summary: PyPreProc is a Python package for correcting, converting, clustering and creating data in Pandas as part of the feature engineering step of the machine learning process.
Home-page: https://github.com/flyandlure/pypreproc
Author: Matt Clarke
Author-email: matt@flyandlure.org
License: MIT
Download-URL: https://github.com/flyandlure/pypreproc/archive/master.zip
Keywords: python,pandas,preprocessing,feature engineering,features,maths
Platform: UNKNOWN
Classifier: Development Status :: 3 - Alpha
Classifier: Intended Audience :: Developers
Classifier: Topic :: Software Development :: Libraries :: Python Modules
Classifier: License :: OSI Approved :: MIT License
Classifier: Programming Language :: Python :: 3.6
Requires-Dist: pandas
Requires-Dist: lifetimes
Requires-Dist: numpy
Requires-Dist: sklearn
Requires-Dist: wheel
Requires-Dist: holidays
